{"time":"2021-07-30T08:40:11+00:00","cloudcannon":{"name":"cloudcannon-jekyll","version":"2.0.1"},"generator":{"name":"jekyll","version":"3.8.5","environment":null,"metadata":{"markdown":"kramdown","kramdown":{"auto_ids":true,"toc_levels":"1..6","entity_output":"as_char","smart_quotes":"lsquo,rsquo,ldquo,rdquo","input":"GFM","hard_wrap":false,"footnote_nr":1,"show_warnings":false},"commonmark":null}},"collections-config":{"posts":{"output":true,"permalink":"/:title/","path":"_posts"},"drafts":{"path":"_drafts"}},"collections":{"drafts":[],"posts":[{"path":"_posts/2019-01-18-charm-old-cities.md","url":"/charm-old-cities/","collection":"posts","id":"/charm-old-cities","draft":false,"categories":["Jekyll","tutorial"],"layout":"post","author":"jane","avatar":"/assets/images/avatar1.jpg","title":"Could we reinvent the charm of old cities","image":"assets/images/home.jpg","tags":["sticky"],"date":"2019-01-18 00:00:00 +0000","slug":"charm-old-cities","ext":".md"},{"path":"_posts/2019-01-18-customer-service.md","url":"/customer-service/","collection":"posts","id":"/customer-service","draft":false,"categories":["Jekyll","tutorial"],"layout":"post","author":"jane","avatar":"/assets/images/avatar1.jpg","title":"What is Jekyll","image":"assets/images/11.jpg","date":"2019-01-18 00:00:00 +0000","slug":"customer-service","ext":".md","tags":[]},{"path":"_posts/2019-01-19-markup-example.md","url":"/markup-example/","collection":"posts","id":"/markup-example","draft":false,"categories":["Jekyll","tutorial"],"layout":"post","author":"jane","avatar":"/assets/images/avatar1.jpg","title":"Markdown Example","image":"assets/images/6.jpg","tags":["featured"],"date":"2019-01-19 00:00:00 +0000","slug":"markup-example","ext":".md"},{"path":"_posts/2019-01-20-quick-start-guide.md","url":"/quick-start-guide/","collection":"posts","id":"/quick-start-guide","draft":false,"categories":["Jekyll","tutorial"],"layout":"post","author":"sal","avatar":"/assets/images/avatar1.jpg","title":"Quick Start Guide","image":"assets/images/12.jpg","date":"2019-01-20 00:00:00 +0000","slug":"quick-start-guide","ext":".md","tags":[]},{"path":"_posts/2019-01-21-is-intelligence-enough.md","url":"/is-intelligence-enough/","collection":"posts","id":"/is-intelligence-enough","draft":false,"categories":["Jekyll","tutorial"],"layout":"post","author":"sal","avatar":"/assets/images/avatar1.jpg","title":"Is Intelligence Enough","image":"https://images.unsplash.com/photo-1523740856324-f2ce89135981?ixlib=rb-1.2.1&auto=format&fit=crop&w=798&q=80","date":"2019-01-21 00:00:00 +0000","slug":"is-intelligence-enough","ext":".md","tags":[]},{"path":"_posts/2019-01-22-never-stopped-worrying-never-loved-bomb.md","url":"/never-stopped-worrying-never-loved-bomb/","collection":"posts","id":"/never-stopped-worrying-never-loved-bomb","draft":false,"categories":["Jekyll"],"layout":"post","author":"sal","avatar":"/assets/images/avatar1.jpg","title":"Never stopped worrying or loving the bomb","image":"assets/images/14.jpg","tags":["featured"],"date":"2019-01-22 00:00:00 +0000","slug":"never-stopped-worrying-never-loved-bomb","ext":".md"},{"path":"_posts/2019-01-23-options-for-creating-new-site-with-jekyll.md","url":"/options-for-creating-new-site-with-jekyll/","collection":"posts","id":"/options-for-creating-new-site-with-jekyll","draft":false,"categories":["Jekyll","tutorial"],"layout":"post","author":"jane","avatar":"/assets/images/avatar1.jpg","title":"Options for creating a new site with Jekyll","image":"assets/images/13.jpg","date":"2019-01-23 00:00:00 +0000","slug":"options-for-creating-new-site-with-jekyll","ext":".md","tags":[]},{"path":"_posts/2019-01-24-powerful-things-markdown-editor.md","url":"/powerful-things-markdown-editor/","collection":"posts","id":"/powerful-things-markdown-editor","draft":false,"categories":["Jekyll","tutorial"],"layout":"post","author":"sal","avatar":"/assets/images/avatar1.jpg","title":"Powerful things you can do with the Markdown editor","image":"assets/images/4.jpg","tags":["featured"],"date":"2019-01-24 00:00:00 +0000","slug":"powerful-things-markdown-editor","ext":".md"},{"path":"_posts/2019-01-25-press-and-education.md","url":"/press-and-education/","collection":"posts","id":"/press-and-education","draft":false,"categories":["Jekyll","tutorial"],"layout":"post","author":"sal","avatar":"/assets/images/avatar1.jpg","title":"Press and education","image":"assets/images/7.jpg","date":"2019-01-25 00:00:00 +0000","slug":"press-and-education","ext":".md","tags":[]},{"path":"_posts/2019-01-26-red-riding.md","url":"/red-riding/","collection":"posts","id":"/red-riding","draft":false,"categories":["Jekyll","tutorial"],"layout":"post","author":"sal","avatar":"/assets/images/avatar1.jpg","title":"Red Riding Hood","image":"assets/images/3.jpg","date":"2019-01-26 00:00:00 +0000","slug":"red-riding","ext":".md","tags":[]},{"path":"_posts/2019-01-27-tree-of-codes.md","url":"/tree-of-codes/","collection":"posts","id":"/tree-of-codes","draft":false,"categories":["Jekyll","tutorial"],"layout":"post","author":"sal","avatar":"/assets/images/avatar1.jpg","title":"Tree of Codes","image":"assets/images/2.jpg","date":"2019-01-27 00:00:00 +0000","slug":"tree-of-codes","ext":".md","tags":[]},{"path":"_posts/2019-01-28-we-all-wait-for-summer.md","url":"/we-all-wait-for-summer/","collection":"posts","id":"/we-all-wait-for-summer","draft":false,"categories":["Jekyll","tutorial"],"layout":"post","author":"jane","avatar":"/assets/images/avatar1.jpg","title":"We all wait for summer","image":"assets/images/1.jpg","tags":["featured"],"date":"2019-01-28 00:00:00 +0000","slug":"we-all-wait-for-summer","ext":".md"},{"path":"_posts/2019-01-29-about-bundler.md","url":"/about-bundler/","collection":"posts","id":"/about-bundler","draft":false,"categories":["Jekyll"],"layout":"post","author":"sal","avatar":"/assets/images/avatar1.jpg","title":"About Bundler","image":"assets/images/2.jpg","date":"2019-01-29 00:00:00 +0000","slug":"about-bundler","ext":".md","tags":[]},{"path":"_posts/2019-01-30-acumulated-experience.md","url":"/acumulated-experience/","collection":"posts","id":"/acumulated-experience","draft":false,"categories":["Jekyll","tutorial"],"layout":"post","author":"sal","avatar":"/assets/images/avatar1.jpg","title":"Accumulated experience of social living","image":"assets/images/15.jpg","date":"2019-01-30 00:00:00 +0000","slug":"acumulated-experience","ext":".md","tags":[]},{"path":"_posts/2019-02-01-education.md","url":"/education/","collection":"posts","id":"/education","draft":false,"categories":["Jekyll","tutorial"],"layout":"post","author":"sal","avatar":"/assets/images/avatar1.jpg","title":"Education must also train one for quick, resolute and effective thinking.","image":"assets/images/3.jpg","date":"2019-02-01 00:00:00 +0000","slug":"education","ext":".md","tags":[]},{"path":"_posts/2019-02-02-first-mass-produced.md","url":"/first-mass-produced/","collection":"posts","id":"/first-mass-produced","draft":false,"categories":["tutorial"],"layout":"post","author":"sal","avatar":"/assets/images/avatar1.jpg","title":"The first mass-produced book to deviate from a rectilinear format","image":"assets/images/17.jpg","tags":["featured"],"date":"2019-02-02 00:00:00 +0000","slug":"first-mass-produced","ext":".md"},{"path":"_posts/2019-02-03-powerful-things-markdown-editor.md","url":"/powerful-things-markdown-editor/","collection":"posts","id":"/powerful-things-markdown-editor","draft":false,"categories":["Jekyll","tutorial"],"layout":"post","author":"jane","avatar":"/assets/images/avatar1.jpg","title":"Powerful things you can do with the Markdown editor","image":"https://images.unsplash.com/photo-1528784351875-d797d86873a1?ixlib=rb-1.2.1&auto=format&fit=crop&w=750&q=80","tags":["summer"],"date":"2019-02-03 00:00:00 +0000","slug":"powerful-things-markdown-editor","ext":".md"},{"path":"_posts/2019-02-04-welcome-to-jekyll.markdown","url":"/welcome-to-jekyll/","collection":"posts","id":"/welcome-to-jekyll","draft":false,"categories":["Jekyll"],"layout":"post","author":"sal","avatar":"/assets/images/avatar1.jpg","title":"Welcome to Jekyll!","image":"assets/images/demo1.jpg","date":"2019-02-04 00:00:00 +0000","slug":"welcome-to-jekyll","ext":".markdown","tags":[]}]},"pages":[{"name":"404.html","path":"404.html","url":"/404/","layout":"default"},{"name":"about.md","path":"_pages/about.md","url":"/about.html","layout":"page-sidebar","title":"About","permalink":"/about.html","image":"/assets/images/screenshot.jpg","comments":true},{"name":"author-jane.html","path":"_pages/author-jane.html","url":"/author-jane.html","layout":"default","title":"Jane","permalink":"/author-jane.html"},{"name":"author-sal.html","path":"_pages/author-sal.html","url":"/author-sal.html","layout":"default","title":"Sal","permalink":"/author-sal.html"},{"name":"authors-list.html","path":"_pages/authors-list.html","url":"/authors-list.html","layout":"default","title":"Authors","permalink":"/authors-list.html"},{"name":"buy-me-a-coffee.md","path":"_pages/buy-me-a-coffee.md","url":"/buy-me-a-coffee.html","layout":"page","title":"Buy me a coffee","permalink":"/buy-me-a-coffee.html"},{"name":"categories.html","path":"_pages/categories.html","url":"/categories.html","layout":"default","title":"Categories","permalink":"/categories.html"},{"name":"contact.md","path":"_pages/contact.md","url":"/contact.html","layout":"page","title":"Contact","permalink":"/contact.html"},{"name":"index.html","path":"index.html","url":"/","title":"InfiOpen Web & Blockchain application development services","layout":"default","pagination":{"enabled":true},"description":"InfiOpen provides software development services in websites, apps, along with blockchain features. Smart contract | ulrta fast static sites | CMS development"},{"name":"privacy-policy.md","path":"_pages/privacy-policy.md","url":"/privacy-policy.html","layout":"page","title":"Privacy Policy","permalink":"/privacy-policy.html"},{"name":"services.md","path":"_pages/services.md","url":"/services.html","layout":"page","title":"Services","permalink":"/services.html"},{"name":"tags.html","path":"_pages/tags.html","url":"/tags.html","layout":"default","title":"Tags","permalink":"/tags.html"},{"name":"index.html","path":"page2/index.html","url":"/page2/","title":"InfiOpen Web & Blockchain application development services","layout":"default","pagination":{"enabled":true},"description":"InfiOpen provides software development services in websites, apps, along with blockchain features. Smart contract | ulrta fast static sites | CMS development"}],"static-pages":[],"base-url":"/mundana-theme-jekyll","paths":{"uploads":null,"data":"_data","pages":"","collections":"","includes":"_includes","layouts":"_layouts"},"_select_data":{"authors":{"sal":{"name":"Sal","site":"https://www.wowthemes.net","avatar":"/assets/images/avatar1.jpg","bio":"Hi, I am Sal, the author of Mundana, the theme you're currently previewing. I hope you like it!","email":"wowthemesnet@gmail.com","twitter":"https://twitter.com/wowthemesnet"},"jane":{"name":"Jane","site":"https://www.wowthemes.net","avatar":"/assets/images/avatar2.jpg","bio":"Blogger, fashionista, love to explore new ideas and write on my morning coffee!","email":"fakemail@gmail.com","twitter":"https://twitter.com/wowthemesnet"}}},"defaults":[{"scope":{"path":"_posts"},"values":{"layout":"post","author":"sal","avatar":"/assets/images/avatar1.jpg"}},{"scope":{"path":"_pages"},"values":{"layout":"page"}}],"source":"","files":{"/_posts/2019-01-26-red-riding.md":"ba8a9c04803cd0238a81473c623fd962","/_posts/2019-01-24-powerful-things-markdown-editor.md":"44802404392651c0dca987a118d5e4d3","/_posts/2019-01-18-customer-service.md":"6d4412f09811c07479959c6a275e744a","/_posts/2019-01-30-acumulated-experience.md":"82d69361092ad869aa01eacdbf021e6e","/_posts/2019-01-27-tree-of-codes.md":"a170363eb9472ea7cf005ada09974972","/_posts/2019-01-23-options-for-creating-new-site-with-jekyll.md":"2a79a387f18be441b4b755cb4033225b","/_posts/2019-02-01-education.md":"3a5b270503613ff46313d1e748c1e3ce","/_posts/2019-02-04-welcome-to-jekyll.markdown":"2a469f05a49a21b4993396ae699a5b31","/_posts/2019-01-21-is-intelligence-enough.md":"cc931b8be8f1a3f6388369fda9ba27b5","/_posts/2019-01-28-we-all-wait-for-summer.md":"a2b396469825b9775ce3a3a23604bc45","/_posts/2019-01-29-about-bundler.md":"35c13448a74db95ee6989973197ba24b","/_posts/2019-02-03-powerful-things-markdown-editor.md":"c8fb6d0735a7711415e0d8588f38d90f","/_posts/2019-01-18-charm-old-cities.md":"c85daf2ef212533eb4f1c8f0ecd0b9f0","/_posts/2019-01-22-never-stopped-worrying-never-loved-bomb.md":"fb786601744ec4f9b566322fc9072a2d","/_posts/2019-01-25-press-and-education.md":"c3668f2fa5e8cc4ec4993885bbf3025d","/_posts/2019-01-19-markup-example.md":"10395793b50ed40bf3da061d488cbf1c","/_posts/2019-01-20-quick-start-guide.md":"fdcb5494c4b64cd437a32c17937c0ddd","/_posts/2019-02-02-first-mass-produced.md":"76f70519d2d0efc43e3ddacdae8bd9c7","/_includes/search-lunr.html":"cdd2e9b7f2066c8b3b0a7e56dd44a604","/_includes/comments.html":"62305f7e6c13b18fd8ec27c8c885f3c9","/_includes/sidebar.html":"49af9e58448614a105db94aeb619fdb8","/_includes/tracking-header.html":"377986f1e3010353696b3f43a1ebbde0","/_includes/meta-read-time.html":"742fc9b285ec0f0aac336064ed7e036a","/_includes/main-loop-card.html":"649ab1898fc38a47e4af61b6c3338515","/_includes/tracking-footer.html":"badb28798567a7c1390e472102efb920","/_includes/sidebar-featured.html":"ffc5b659927c557e71df20f256f1c3b4","/_includes/menu-header.html":"2391b5072742bae0f19009291a82c03f","/_layouts/default.html":"7c5f165faffa6f90f7440b6a0a4c28de","/_layouts/page-sidebar.html":"0225ee2dfe10d2af26df0c1bbaa4aa68","/_layouts/page.html":"89497710e5725a63c2f042a5654ca760","/_layouts/post.html":"3f7e4e2cdf27657c2b743a5615fa74ad","/Gemfile":"c9f0b6df2d5559e50f166a5f1d668c55","/.github/FUNDING.yml":"b9924e589a1b9e71721b2d036ac8e8ed","/index.html":"e518e3b1cf40de4f294c36a5c0503a58","/assets/js/lunr.js":"a5802d96e7726edf965526075d62e86e","/assets/js/theme.js":"8dba3a351a857030b523ca1cc5c6f3ba","/assets/js/bootstrap.js":"eb5fac582a82f296aeb74900b01a2fa3","/assets/images/15.jpg":"6b1e39c084bc4231fde597554f5731f9","/assets/images/7.jpg":"ff343fd8395d852592b6d1e92d77dee6","/assets/images/8.jpg":"80ebed22e487d0bfbda03e7815e0886d","/assets/images/home.jpg":"894b8037f0d286994b8776505a6d8c32","/assets/images/16.jpg":"57c75b4720b1d7bd79b18ddb0ae158d6","/assets/images/3.jpg":"7531d747d542a04a07001a433c387f61","/assets/images/14.jpg":"8fcadfacdf660acdab1a154861457486","/assets/images/demo1.jpg":"c9a1f98da32453ce437482addacbfc1a","/assets/images/jekyll.svg":"c8e221542a14f9a1ba6a4132b438773f","/assets/images/17.jpg":"4226b16bb0dd3caf4a53820ca4a8acbd","/assets/images/favicon.ico":"c66a0fcd6276b57ef6ff576beba26027","/assets/images/5.jpg":"936050f915b580d7cf56b36eb47d1698","/assets/images/11.jpg":"785861130eb59496f26e84d812a03829","/assets/images/10.jpg":"05d31a9177c90496699a5bc511c25b7f","/assets/images/avatar1.jpg":"805b30426091c11a1260165ed802af3b","/assets/images/screenshot.jpg":"abf3084b14112d8e85de6cd620697185","/assets/images/13.jpg":"8e72e6c1192b1879b8e1bd078277a8da","/assets/images/6.jpg":"b9bfdc5b5b238ab57538cdd368d0a9bb","/assets/images/12.jpg":"f2a4ddb3786805553c7502be279b5ea6","/assets/images/9.jpg":"dbf527ede1fb60725b4f34c746bf63fd","/assets/images/2.jpg":"1df8bdfac27e574ecfeba1889a717dc5","/assets/images/avatar2.jpg":"e57117fe2615194038c5534885151b93","/assets/images/4.jpg":"180d047cbe7f07610c8dc7e5fd816f83","/assets/images/1.jpg":"01cb07c9410f092b758e5326f9620500","/assets/css/main.css":"f9b410e0efbc07451ad70265b9ec49f4","/assets/css/theme.css":"3d33a9ca7dfa36d0d7880db4980e0e9d","/_pages/about.md":"44317fcba4db4e527c81a62b57d665ff","/_pages/author-sal.html":"cfbe9f3059d2c137707705fd955269bc","/_pages/author-jane.html":"c7c120bb3049170b16d9c417e18e6775","/_pages/services.md":"7994aa68e18808bf5a389f8f09cc87ad","/_pages/authors-list.html":"0e60f2a3382222be3897d16f827858d0","/_pages/privacy-policy.md":"2b24b712164c53a2b1200d049610965d","/_pages/buy-me-a-coffee.md":"03a49d8862d135e95b88dc7333a48bca","/_pages/tags.html":"4a469417b1ab2f01b06495c8e3578888","/_pages/categories.html":"2957265282402327299b166b55342a77","/_pages/contact.md":"c12d8d12086904d1e5b917ad01135447","/.gitignore":"a7197de1566fe5facd2d816e3365d241","/_config.yml":"5590dc254a3a7d2d5e8a866917dffd55","/404.html":"58b018699a2b561eae961bf7f0a712a1","/Gemfile.lock":"87884684d5a2d3b9900c6012e586dc8e","/docker-compose.yml":"3c5ce90ee6208b8024c111fa5ac5b4b3","/README.md":"58f2b5c6aa7acdea8e7881dcae2a6bbc"}}